healthcheck_reporter/__init__.py
healthcheck_reporter/core/config.py
healthcheck_reporter/core/models.py
healthcheck_reporter/probes/db_probe.py
healthcheck_reporter/reporter/report_builder.py
healthcheck_reporter/reporter/reporter.py
healthcheck_reporter/transport/api_server.py
healthcheck_reporter/transport/mqtt_publisher.py
healthcheck_reporter-0.3.2.dist-info/METADATA
healthcheck_reporter-0.3.2.dist-info/WHEEL
healthcheck_reporter-0.3.2.dist-info/RECORD
