Metadata-Version: 2.4
Name: healthcheck-reporter
Version: 0.3.2
Summary: A health checker package to report using MQTT
Project-URL: Homepage, https://github.com/fernandodazadev/healthcheck-reporter
Project-URL: Changelog, https://github.com/fernandodazadev/healthcheck-reporter/blob/main/CHANGELOG.md
Author-email: Fernando González <fernando.daza.dev@gmail.com>
Requires-Python: >=3.8
Requires-Dist: fastapi<1.0.0,>=0.104.0
Requires-Dist: paho-mqtt<2.0.0,>=1.6.1
Requires-Dist: prometheus-client<1.0.0,>=0.19.0
Requires-Dist: psycopg2-binary<3.0,>=2.9
Requires-Dist: requests<3.0.0,>=2.31.0
Requires-Dist: uvicorn<1.0.0,>=0.24.0
Provides-Extra: dev
Requires-Dist: pylint<4.0,>=3.2; extra == 'dev'
